{
  "id": "cat",
  "name": "Cat",
  "category": "animals",
  "description": "A sitting cat with pointy ears and curved tail",
  "tags": ["cat", "kitten", "feline", "pet", "meow"],
  "thumbnailDescription": "Orange cat with pointy ears",
  "tiles": [
    {"tileType": "ISOSCELES_TRIANGLE", "x": 9, "y": 0, "rotation": "R0", "color": "ORANGE"},
    {"tileType": "ISOSCELES_TRIANGLE", "x": 15, "y": 0, "rotation": "R0", "color": "ORANGE"},
    {"tileType": "SOLID_SQUARE", "x": 9, "y": 3, "rotation": "R0", "color": "ORANGE"},
    {"tileType": "SOLID_SQUARE", "x": 12, "y": 3, "rotation": "R0", "color": "ORANGE"},
    {"tileType": "SOLID_SQUARE", "x": 15, "y": 3, "rotation": "R0", "color": "ORANGE"},
    {"tileType": "SOLID_SQUARE", "x": 9, "y": 6, "rotation": "R0", "color": "ORANGE"},
    {"tileType": "WINDOW_SQUARE", "x": 12, "y": 6, "rotation": "R0", "color": "GREEN"},
    {"tileType": "SOLID_SQUARE", "x": 15, "y": 6, "rotation": "R0", "color": "ORANGE"},
    {"tileType": "SOLID_SQUARE", "x": 9, "y": 9, "rotation": "R0", "color": "ORANGE"},
    {"tileType": "EQUILATERAL_TRIANGLE", "x": 12, "y": 9, "rotation": "R0", "color": "PINK"},
    {"tileType": "SOLID_SQUARE", "x": 15, "y": 9, "rotation": "R0", "color": "ORANGE"},
    {"tileType": "SOLID_SQUARE", "x": 9, "y": 12, "rotation": "R0", "color": "ORANGE"},
    {"tileType": "SOLID_SQUARE", "x": 12, "y": 12, "rotation": "R0", "color": "ORANGE"},
    {"tileType": "SOLID_SQUARE", "x": 15, "y": 12, "rotation": "R0", "color": "ORANGE"},
    {"tileType": "SOLID_SQUARE", "x": 9, "y": 15, "rotation": "R0", "color": "ORANGE"},
    {"tileType": "SOLID_SQUARE", "x": 12, "y": 15, "rotation": "R0", "color": "ORANGE"},
    {"tileType": "SOLID_SQUARE", "x": 15, "y": 15, "rotation": "R0", "color": "ORANGE"},
    {"tileType": "SOLID_SQUARE", "x": 9, "y": 18, "rotation": "R0", "color": "ORANGE"},
    {"tileType": "SOLID_SQUARE", "x": 12, "y": 18, "rotation": "R0", "color": "ORANGE"},
    {"tileType": "SOLID_SQUARE", "x": 15, "y": 18, "rotation": "R0", "color": "ORANGE"},
    {"tileType": "SOLID_SQUARE", "x": 9, "y": 21, "rotation": "R0", "color": "ORANGE"},
    {"tileType": "SOLID_SQUARE", "x": 12, "y": 21, "rotation": "R0", "color": "ORANGE"},
    {"tileType": "SOLID_SQUARE", "x": 15, "y": 21, "rotation": "R0", "color": "ORANGE"},
    {"tileType": "SOLID_SQUARE", "x": 6, "y": 24, "rotation": "R0", "color": "ORANGE"},
    {"tileType": "SOLID_SQUARE", "x": 9, "y": 24, "rotation": "R0", "color": "ORANGE"},
    {"tileType": "SOLID_SQUARE", "x": 12, "y": 24, "rotation": "R0", "color": "ORANGE"},
    {"tileType": "SOLID_SQUARE", "x": 15, "y": 24, "rotation": "R0", "color": "ORANGE"},
    {"tileType": "SOLID_SQUARE", "x": 18, "y": 24, "rotation": "R0", "color": "ORANGE"},
    {"tileType": "RIGHT_TRIANGLE", "x": 18, "y": 12, "rotation": "R0", "color": "ORANGE"},
    {"tileType": "RIGHT_TRIANGLE", "x": 21, "y": 9, "rotation": "R90", "color": "ORANGE"},
    {"tileType": "RIGHT_TRIANGLE", "x": 21, "y": 6, "rotation": "R0", "color": "ORANGE"}
  ]
}
